yandex_tank_api_client/__init__.py
yandex_tank_api_client/async.py
yandex_tank_api_client/session.py
yandex_tank_api_client-0.0.3.dist-info/DESCRIPTION.rst
yandex_tank_api_client-0.0.3.dist-info/METADATA
yandex_tank_api_client-0.0.3.dist-info/metadata.json
yandex_tank_api_client-0.0.3.dist-info/RECORD
yandex_tank_api_client-0.0.3.dist-info/top_level.txt
yandex_tank_api_client-0.0.3.dist-info/WHEEL
