Metadata-Version: 2.0
Name: yandex-tank-api-client
Version: 0.0.3
Summary: yandex-tank-api client python module
Home-page: UNKNOWN
Author: UNKNOWN
Author-email: UNKNOWN
License: UNKNOWN
Platform: UNKNOWN
Requires-Dist: trollius
